# 装饰器
**装饰器是可调用对象，其参数是另外一个函数。装饰器可能会处理被装饰的函数，然后将其返回，也可以替换成另外一个函数或者可调用对象--流畅的python**

> 装饰器会在被装饰的函数定义之后立即运行
```python
def deco(func):
    print("running deco")

    def inner():
        # print('running inner()')
        func()
    return inner


@deco
def target():
    print('running target()')
```
> 输出
```shell
(venv) sh-4.2# /data/flask-study/venv/bin/python3.6 /data/flask-study/project/test23.py
running deco
```
# 闭包
> 理解闭包需要先理解变量的作用域
```shell
In [1]: b=1

In [2]: def test():
   ...:     a=2
   ...:     print(a)
   ...:     print(b)
   ...: 

In [3]: test()
2
1
In [5]: dis.dis(test)
  2           0 LOAD_CONST               1 (2)
              2 STORE_FAST               0 (a)

  3           4 LOAD_GLOBAL              0 (print)
              6 LOAD_FAST                0 (a)
              8 CALL_FUNCTION            1
             10 POP_TOP

  4          12 LOAD_GLOBAL              0 (print)
             14 LOAD_GLOBAL              1 (b)
             16 CALL_FUNCTION            1
             18 POP_TOP
             20 LOAD_CONST               0 (None)
             22 RETURN_VALUE

In [6]: def test1():
   ...:     a=2
   ...:     print(a)
   ...:     print(b)
   ...:     b=3
   ...: 

In [7]: test1()
2
---------------------------------------------------------------------------
UnboundLocalError                         Traceback (most recent call last)
<ipython-input-7-51a57b51f630> in <module>
----> 1 test1()

<ipython-input-6-da68a6feef59> in test1()
      2     a=2
      3     print(a)
----> 4     print(b)
      5     b=3
      6 

UnboundLocalError: local variable 'b' referenced before assignment
In [8]: dis.dis(test1)
  2           0 LOAD_CONST               1 (2)
              2 STORE_FAST               0 (a)

  3           4 LOAD_GLOBAL              0 (print)
              6 LOAD_FAST                0 (a)
              8 CALL_FUNCTION            1
             10 POP_TOP

  4          12 LOAD_GLOBAL              0 (print)
             14 LOAD_FAST                1 (b)
             16 CALL_FUNCTION            1
             18 POP_TOP

  5          20 LOAD_CONST               2 (3)
             22 STORE_FAST               1 (b)
             24 LOAD_CONST               0 (None)
             26 RETURN_VALUE

# 通过global强制声明
In [9]: def test1():
   ...:     a=2
   ...:     global b
   ...:     print(a)
   ...:     print(b)
   ...:     b=3
   ...: 

In [10]: 

In [10]: test1()
2
1

In [11]: 
```

> 闭包现象
```python
def make_avg():
    series = []

    def averager(new_values):
        series.append(new_values)
        series_total = sum(series)
        return series_total/len(series)
    return averager
```

> 输出
```shell
In [1]: from test22 import make_avg

In [2]: avg=make_avg()

In [3]: avg(10)
Out[3]: 10.0

In [4]: avg(11)
Out[4]: 10.5

In [5]: avg(12)
Out[5]: 11.0

In [7]: print(avg.__code__.co_freevars)
('series',)

In [8]: 
```
**在make_avg（）实例化之后，series的生命周期应该就结束了，但是执行结果看，这个变量一直可以使用,叫做自由变量，特指在嵌套函数中使用的除全局变量的外部变量**

> 再看下面的例子
```python
def make_avg():
    count = int()
    total = int()

    def averager(new_values):
        count += 1
        total += new_values
        return total/count
    return averager

In [3]: avg(10)
---------------------------------------------------------------------------
UnboundLocalError                         Traceback (most recent call last)
<ipython-input-3-ace390caaa2e> in <module>
----> 1 avg(10)

/data/flask-study/project/test22.py in averager(new_values)
    450 
    451     def averager(new_values):
--> 452         count += 1
    453         total += new_values
    454         return total/count

UnboundLocalError: local variable 'count' referenced before assignment
```

**这里count,total是int类型，属于不可变类型，当尝试累加的时候，其实py会重新申请一个内部变量count来计算，但是内部变量count未声明，所以报错了，可以使用nonlocal来解决**
```python
def make_avg():
    count = int()
    total = int()

    def averager(new_values):
        nonlocal count, total
        count += 1
        total += new_values
        return total/count
    return averager

    In [1]: from test22 import make_avg

In [2]: avg=make_avg()

In [3]: avg(10)
Out[3]: 10.0

In [4]: 
```